[
 {
  "pair_id": "n2_Sunan-Abu-Dawud-35.4232#437",
  "e1_word": "\nNarrate",
  "e1_off": 397,
  "e1_class": "REPORTING",
  "e1_tense": "PAST",
  "e1_aspect": "NONE",
  "e1_sentence": "Narrated Hudhayfah ibn al-Yaman: Subay' ibn Khalid said:  I came to Kufah at the time when Tustar was conquered",
  "e2_word": " sai",
  "e2_off": 448,
  "e2_class": "REPORTING",
  "e2_tense": "PAST",
  "e2_aspect": "NONE",
  "e2_sentence": "Narrated Hudhayfah ibn al-Yaman: Subay' ibn Khalid said:  I came to Kufah at the time when Tustar was conquered",
  "same_sentence": true,
  "text_order": "e1_first",
  "signal": "",
  "relation": "AFTER"
 },
 {
  "pair_id": "n2_Sunan-Abu-Dawud-35.4232#438",
  "e1_word": " sai",
  "e1_off": 448,
  "e1_class": "REPORTING",
  "e1_tense": "PAST",
  "e1_aspect": "NONE",
  "e1_sentence": "Narrated Hudhayfah ibn al-Yaman: Subay' ibn Khalid said:  I came to Kufah at the time when Tustar was conquered",
  "e2_word": " sai",
  "e2_off": 1905,
  "e2_class": "REPORTING",
  "e2_tense": "PAST",
  "e2_aspect": "NONE",
  "e2_sentence": "He said: 'The Last Hour  will come.",
  "same_sentence": false,
  "text_order": "e1_first",
  "signal": "",
  "relation": "AFTER"
 },
 {
  "pair_id": "n2_Sunan-Abu-Dawud-35.4232#441",
  "e1_word": " cam",
  "e1_off": 457,
  "e1_class": "OCCURRENCE",
  "e1_tense": "PAST",
  "e1_aspect": "NONE",
  "e1_sentence": "Narrated Hudhayfah ibn al-Yaman: Subay' ibn Khalid said:  I came to Kufah at the time when Tustar was conquered",
  "e2_word": " too",
  "e2_off": 512,
  "e2_class": "OCCURRENCE",
  "e2_tense": "PAST",
  "e2_aspect": "NONE",
  "e2_sentence": "I took some mules from  it",
  "same_sentence": false,
  "text_order": "e1_first",
  "signal": "",
  "relation": "BEFORE"
 },
 {
  "pair_id": "n2_Sunan-Abu-Dawud-35.4232#442",
  "e1_word": " too",
  "e1_off": 512,
  "e1_class": "OCCURRENCE",
  "e1_tense": "PAST",
  "e1_aspect": "NONE",
  "e1_sentence": "I took some mules from  it",
  "e2_word": " entere",
  "e2_off": 545,
  "e2_class": "OCCURRENCE",
  "e2_tense": "PAST",
  "e2_aspect": "NONE",
  "e2_sentence": "When I entered the mosque (of Kufah), I found there some people of  moderate stature, and among them was a man whom you could recognize when you  saw him that he was from the people of Hijaz",
  "same_sentence": false,
  "text_order": "e1_first",
  "signal": "",
  "relation": "BEFORE"
 },
 {
  "pair_id": "n2_Sunan-Abu-Dawud-35.4232#478",
  "e1_word": " entere",
  "e1_off": 545,
  "e1_class": "OCCURRENCE",
  "e1_tense": "PAST",
  "e1_aspect": "NONE",
  "e1_sentence": "When I entered the mosque (of Kufah), I found there some people of  moderate stature, and among them was a man whom you could recognize when you  saw him that he was from the people of Hijaz",
  "e2_word": " foun",
  "e2_off": 578,
  "e2_class": "OCCURRENCE",
  "e2_tense": "PAST",
  "e2_aspect": "NONE",
  "e2_sentence": "When I entered the mosque (of Kufah), I found there some people of  moderate stature, and among them was a man whom you could recognize when you  saw him that he was from the people of Hijaz",
  "same_sentence": true,
  "text_order": "e1_first",
  "signal": "33",
  "relation": "IBEFORE"
 },
 {
  "pair_id": "n2_Sunan-Abu-Dawud-35.4232#444",
  "e1_word": " foun",
  "e1_off": 578,
  "e1_class": "OCCURRENCE",
  "e1_tense": "PAST",
  "e1_aspect": "NONE",
  "e1_sentence": "When I entered the mosque (of Kufah), I found there some people of  moderate stature, and among them was a man whom you could recognize when you  saw him that he was from the people of Hijaz",
  "e2_word": " among them wa",
  "e2_off": 628,
  "e2_class": "STATE",
  "e2_tense": "PAST",
  "e2_aspect": "NONE",
  "e2_sentence": "When I entered the mosque (of Kufah), I found there some people of  moderate stature, and among them was a man whom you could recognize when you  saw him that he was from the people of Hijaz",
  "same_sentence": true,
  "text_order": "e1_first",
  "signal": "",
  "relation": "IS_INCLUDED"
 },
 {
  "pair_id": "n2_Sunan-Abu-Dawud-35.4232#479",
  "e1_word": " foun",
  "e1_off": 578,
  "e1_class": "OCCURRENCE",
  "e1_tense": "PAST",
  "e1_aspect": "NONE",
  "e1_sentence": "When I entered the mosque (of Kufah), I found there some people of  moderate stature, and among them was a man whom you could recognize when you  saw him that he was from the people of Hijaz",
  "e2_word": " aske",
  "e2_off": 732,
  "e2_class": "REPORTING",
  "e2_tense": "PAST",
  "e2_aspect": "NONE",
  "e2_sentence": "I asked: 'Who is he?",
  "same_sentence": false,
  "text_order": "e1_first",
  "signal": "",
  "relation": "BEFORE"
 },
 {
  "pair_id": "n2_Sunan-Abu-Dawud-35.4232#445",
  "e1_word": " among them wa",
  "e1_off": 628,
  "e1_class": "STATE",
  "e1_tense": "PAST",
  "e1_aspect": "NONE",
  "e1_sentence": "When I entered the mosque (of Kufah), I found there some people of  moderate stature, and among them was a man whom you could recognize when you  saw him that he was from the people of Hijaz",
  "e2_word": " aske",
  "e2_off": 732,
  "e2_class": "REPORTING",
  "e2_tense": "PAST",
  "e2_aspect": "NONE",
  "e2_sentence": "I asked: 'Who is he?",
  "same_sentence": false,
  "text_order": "e1_first",
  "signal": "",
  "relation": "INCLUDES"
 },
 {
  "pair_id": "n2_Sunan-Abu-Dawud-35.4232#446",
  "e1_word": " aske",
  "e1_off": 732,
  "e1_class": "REPORTING",
  "e1_tense": "PAST",
  "e1_aspect": "NONE",
  "e1_sentence": "I asked: 'Who is he?",
  "e2_word": "\nfrowne",
  "e2_off": 764,
  "e2_class": "OCCURRENCE",
  "e2_tense": "PAST",
  "e2_aspect": "NONE",
  "e2_sentence": "The people  frowned at me and said: 'Do you not recognize him",
  "same_sentence": false,
  "text_order": "e1_first",
  "signal": "",
  "relation": "BEFORE"
 },
 {
  "pair_id": "n2_Sunan-Abu-Dawud-35.4232#447",
  "e1_word": "\nfrowne",
  "e1_off": 764,
  "e1_class": "OCCURRENCE",
  "e1_tense": "PAST",
  "e1_aspect": "NONE",
  "e1_sentence": "The people  frowned at me and said: 'Do you not recognize him",
  "e2_word": " sai",
  "e2_off": 782,
  "e2_class": "REPORTING",
  "e2_tense": "PAST",
  "e2_aspect": "NONE",
  "e2_sentence": "The people  frowned at me and said: 'Do you not recognize him",
  "same_sentence": true,
  "text_order": "e1_first",
  "signal": "",
  "relation": "IBEFORE"
 },
 {
  "pair_id": "n2_Sunan-Abu-Dawud-35.4232#448",
  "e1_word": " sai",
  "e1_off": 782,
  "e1_class": "REPORTING",
  "e1_tense": "PAST",
  "e1_aspect": "NONE",
  "e1_sentence": "The people  frowned at me and said: 'Do you not recognize him",
  "e2_word": " sai",
  "e2_off": 924,
  "e2_class": "REPORTING",
  "e2_tense": "PAST",
  "e2_aspect": "NONE",
  "e2_sentence": "Then  Hudhayfah said: 'People used to ask the Apostle of Allah (peace be upon him)  about good, and I used to ask him about evil",
  "same_sentence": false,
  "text_order": "e1_first",
  "signal": "122",
  "relation": "IBEFORE"
 },
 {
  "pair_id": "n2_Sunan-Abu-Dawud-35.4232#451",
  "e1_word": " sai",
  "e1_off": 924,
  "e1_class": "REPORTING",
  "e1_tense": "PAST",
  "e1_aspect": "NONE",
  "e1_sentence": "Then  Hudhayfah said: 'People used to ask the Apostle of Allah (peace be upon him)  about good, and I used to ask him about evil",
  "e2_word": " stare",
  "e2_off": 1054,
  "e2_class": "PERCEPTION",
  "e2_tense": "PAST",
  "e2_aspect": "NONE",
  "e2_sentence": "Then the people stared hard at  him.",
  "same_sentence": false,
  "text_order": "e1_first",
  "signal": "153",
  "relation": "IBEFORE"
 },
 {
  "pair_id": "n2_Sunan-Abu-Dawud-35.4232#452",
  "e1_word": " stare",
  "e1_off": 1054,
  "e1_class": "PERCEPTION",
  "e1_tense": "PAST",
  "e1_aspect": "NONE",
  "e1_sentence": "Then the people stared hard at  him.",
  "e2_word": " sai",
  "e2_off": 1079,
  "e2_class": "REPORTING",
  "e2_tense": "PAST",
  "e2_aspect": "NONE",
  "e2_sentence": "He said: 'I know the reason why you dislike it.",
  "same_sentence": false,
  "text_order": "e1_first",
  "signal": "",
  "relation": "BEFORE"
 },
 {
  "pair_id": "n2_Sunan-Abu-Dawud-35.4232#453",
  "e1_word": " sai",
  "e1_off": 1079,
  "e1_class": "REPORTING",
  "e1_tense": "PAST",
  "e1_aspect": "NONE",
  "e1_sentence": "He said: 'I know the reason why you dislike it.",
  "e2_word": " aske",
  "e2_off": 1132,
  "e2_class": "REPORTING",
  "e2_tense": "PAST",
  "e2_aspect": "NONE",
  "e2_sentence": "I then asked: 'Apostle  of Allah, will there be evil as there was before, after this good which Allah  has bestowed on us?",
  "same_sentence": false,
  "text_order": "e1_first",
  "signal": "176",
  "relation": "IBEFORE"
 },
 {
  "pair_id": "n2_Sunan-Abu-Dawud-35.4232#454",
  "e1_word": " aske",
  "e1_off": 1132,
  "e1_class": "REPORTING",
  "e1_tense": "PAST",
  "e1_aspect": "NONE",
  "e1_sentence": "I then asked: 'Apostle  of Allah, will there be evil as there was before, after this good which Allah  has bestowed on us?",
  "e2_word": " replie",
  "e2_off": 1252,
  "e2_class": "REPORTING",
  "e2_tense": "PAST",
  "e2_aspect": "NONE",
  "e2_sentence": "He replied: 'Yes.",
  "same_sentence": false,
  "text_order": "e1_first",
  "signal": "",
  "relation": "IBEFORE"
 },
 {
  "pair_id": "n2_Sunan-Abu-Dawud-35.4232#467",
  "e1_word": " will there be evil as there was befor",
  "e1_off": 1159,
  "e1_class": "STATE",
  "e1_tense": "FUTURE",
  "e1_aspect": "NONE",
  "e1_sentence": "I then asked: 'Apostle  of Allah, will there be evil as there was before, after this good which Allah  has bestowed on us?",
  "e2_word": "\nhas bestowe",
  "e2_off": 1228,
  "e2_class": "OCCURRENCE",
  "e2_tense": "PRESENT",
  "e2_aspect": "PERFECT",
  "e2_sentence": "I then asked: 'Apostle  of Allah, will there be evil as there was before, after this good which Allah  has bestowed on us?",
  "same_sentence": true,
  "text_order": "e1_first",
  "signal": "193",
  "relation": "AFTER"
 },
 {
  "pair_id": "n2_Sunan-Abu-Dawud-35.4232#455",
  "e1_word": " replie",
  "e1_off": 1252,
  "e1_class": "REPORTING",
  "e1_tense": "PAST",
  "e1_aspect": "NONE",
  "e1_sentence": "He replied: 'Yes.",
  "e2_word": " aske",
  "e2_off": 1270,
  "e2_class": "REPORTING",
  "e2_tense": "PAST",
  "e2_aspect": "NONE",
  "e2_sentence": "I asked: 'Wherein does the protection  from it lie?",
  "same_sentence": false,
  "text_order": "e1_first",
  "signal": "",
  "relation": "IBEFORE"
 },
 {
  "pair_id": "n2_Sunan-Abu-Dawud-35.4232#456",
  "e1_word": " aske",
  "e1_off": 1270,
  "e1_class": "REPORTING",
  "e1_tense": "PAST",
  "e1_aspect": "NONE",
  "e1_sentence": "I asked: 'Wherein does the protection  from it lie?",
  "e2_word": " replie",
  "e2_off": 1324,
  "e2_class": "REPORTING",
  "e2_tense": "PAST",
  "e2_aspect": "NONE",
  "e2_sentence": "He replied: 'In the sword.",
  "same_sentence": false,
  "text_order": "e1_first",
  "signal": "",
  "relation": "IBEFORE"
 },
 {
  "pair_id": "n2_Sunan-Abu-Dawud-35.4232#457",
  "e1_word": " replie",
  "e1_off": 1324,
  "e1_class": "REPORTING",
  "e1_tense": "PAST",
  "e1_aspect": "NONE",
  "e1_sentence": "He replied: 'In the sword.",
  "e2_word": " aske",
  "e2_off": 1351,
  "e2_class": "REPORTING",
  "e2_tense": "PAST",
  "e2_aspect": "NONE",
  "e2_sentence": "I asked: 'Apostle of Allah, what  will then happen?",
  "same_sentence": false,
  "text_order": "e1_first",
  "signal": "",
  "relation": "IBEFORE"
 },
 {
  "pair_id": "n2_Sunan-Abu-Dawud-35.4232#459",
  "e1_word": " aske",
  "e1_off": 1351,
  "e1_class": "REPORTING",
  "e1_tense": "PAST",
  "e1_aspect": "NONE",
  "e1_sentence": "I asked: 'Apostle of Allah, what  will then happen?",
  "e2_word": " replie",
  "e2_off": 1405,
  "e2_class": "REPORTING",
  "e2_tense": "PAST",
  "e2_aspect": "NONE",
  "e2_sentence": "He replied: 'If Allah has on Earth a caliph who flays your  back and takes your property, obey him, otherwise die holding onto the stump  of a tree.",
  "same_sentence": false,
  "text_order": "e1_first",
  "signal": "",
  "relation": "IBEFORE"
 },
 {
  "pair_id": "n2_Sunan-Abu-Dawud-35.4232#460",
  "e1_word": " replie",
  "e1_off": 1405,
  "e1_class": "REPORTING",
  "e1_tense": "PAST",
  "e1_aspect": "NONE",
  "e1_sentence": "He replied: 'If Allah has on Earth a caliph who flays your  back and takes your property, obey him, otherwise die holding onto the stump  of a tree.",
  "e2_word": " aske",
  "e2_off": 1554,
  "e2_class": "REPORTING",
  "e2_tense": "PAST",
  "e2_aspect": "NONE",
  "e2_sentence": "I asked: 'What will come next?",
  "same_sentence": false,
  "text_order": "e1_first",
  "signal": "",
  "relation": "IBEFORE"
 },
 {
  "pair_id": "n2_Sunan-Abu-Dawud-35.4232#461",
  "e1_word": " aske",
  "e1_off": 1554,
  "e1_class": "REPORTING",
  "e1_tense": "PAST",
  "e1_aspect": "NONE",
  "e1_sentence": "I asked: 'What will come next?",
  "e2_word": " replie",
  "e2_off": 1587,
  "e2_class": "REPORTING",
  "e2_tense": "PAST",
  "e2_aspect": "NONE",
  "e2_sentence": "He replied: 'Then the Antichrist  (Dajjal) will come forth accompanied by a river and fire",
  "same_sentence": false,
  "text_order": "e1_first",
  "signal": "",
  "relation": "IBEFORE"
 },
 {
  "pair_id": "n2_Sunan-Abu-Dawud-35.4232#462",
  "e1_word": " replie",
  "e1_off": 1587,
  "e1_class": "REPORTING",
  "e1_tense": "PAST",
  "e1_aspect": "NONE",
  "e1_sentence": "He replied: 'Then the Antichrist  (Dajjal) will come forth accompanied by a river and fire",
  "e2_word": " aske",
  "e2_off": 1872,
  "e2_class": "REPORTING",
  "e2_tense": "PAST",
  "e2_aspect": "NONE",
  "e2_sentence": "I then asked: 'What will come next?",
  "same_sentence": false,
  "text_order": "e1_first",
  "signal": "352",
  "relation": "IBEFORE"
 },
 {
  "pair_id": "n2_Sunan-Abu-Dawud-35.4232#472",
  "e1_word": " will come fort",
  "e1_off": 1627,
  "e1_class": "OCCURRENCE",
  "e1_tense": "FUTURE",
  "e1_aspect": "NONE",
  "e1_sentence": "He replied: 'Then the Antichrist  (Dajjal) will come forth accompanied by a river and fire",
  "e2_word": " accompanie",
  "e2_off": 1643,
  "e2_class": "OCCURRENCE",
  "e2_tense": "PASTPART",
  "e2_aspect": "NONE",
  "e2_sentence": "He replied: 'Then the Antichrist  (Dajjal) will come forth accompanied by a river and fire",
  "same_sentence": true,
  "text_order": "e1_first",
  "signal": "",
  "relation": "SIMULTANEOUS"
 },
 {
  "pair_id": "n2_Sunan-Abu-Dawud-35.4232#463",
  "e1_word": " aske",
  "e1_off": 1872,
  "e1_class": "REPORTING",
  "e1_tense": "PAST",
  "e1_aspect": "NONE",
  "e1_sentence": "I then asked: 'What will come next?",
  "e2_word": " sai",
  "e2_off": 1905,
  "e2_class": "REPORTING",
  "e2_tense": "PAST",
  "e2_aspect": "NONE",
  "e2_sentence": "He said: 'The Last Hour  will come.",
  "same_sentence": false,
  "text_order": "e1_first",
  "signal": "",
  "relation": "IBEFORE"
 }
]