[{"pair_id": "VOA19980303.1600.2745.tml_ei50053_ei50052", "e1_word": "reports", "e1_class": "REPORTING", "e1_tense": "NONE", "e1_aspect": "NONE", "e1_off": 6180, "e2_word": "received", "e2_class": "OCCURRENCE", "e2_tense": "PAST", "e2_aspect": "NONE", "e2_off": 6102, "same_sentence": true, "text_order": "e2_first", "e1_sentence": "", "e2_sentence": "", "signal": "", "relation": "BEFORE"}, {"pair_id": "VOA19980303.1600.2745.tml_ei50002_ei50001", "e1_word": "blessing", "e1_class": "OCCURRENCE", "e1_tense": "NONE", "e1_aspect": "NONE", "e1_off": 427, "e2_word": "expansion", "e2_class": "OCCURRENCE", "e2_tense": "NONE", "e2_aspect": "NONE", "e2_off": 347, "same_sentence": true, "text_order": "e2_first", "e1_sentence": "", "e2_sentence": "", "signal": "", "relation": "IDENTITY"}, {"pair_id": "VOA19980303.1600.2745.tml_ei50006_ei50007", "e1_word": "rise", "e1_class": "OCCURRENCE", "e1_tense": "PRESENT", "e1_aspect": "PERFECTIVE", "e1_off": 853, "e2_word": "growth", "e2_class": "OCCURRENCE", "e2_tense": "NONE", "e2_aspect": "NONE", "e2_off": 908, "same_sentence": true, "text_order": "e1_first", "e1_sentence": "", "e2_sentence": "", "signal": "", "relation": "IS_INCLUDED"}, {"pair_id": "VOA19980303.1600.2745.tml_ei50004_ei50008", "e1_word": "used", "e1_class": "OCCURRENCE", "e1_tense": "PRESENT", "e1_aspect": "PROGRESSIVE", "e1_off": 682, "e2_word": "using", "e2_class": "OCCURRENCE", "e2_tense": "PRESENT", "e2_aspect": "PROGRESSIVE", "e2_off": 1189, "same_sentence": false, "text_order": "e1_first", "e1_sentence": "", "e2_sentence": "", "signal": "", "relation": "IDENTITY"}, {"pair_id": "VOA19980303.1600.2745.tml_ei50010_ei50005", "e1_word": "monitored", "e1_class": "OCCURRENCE", "e1_tense": "PRESENT", "e1_aspect": "PERFECTIVE", "e1_off": 1513, "e2_word": "says", "e2_class": "REPORTING", "e2_tense": "PRESENT", "e2_aspect": "NONE", "e2_off": 780, "same_sentence": false, "text_order": "e2_first", "e1_sentence": "", "e2_sentence": "", "signal": "", "relation": "BEFORE"}, {"pair_id": "VOA19980303.1600.2745.tml_ei50013_ei50005", "e1_word": "warns", "e1_class": "I_ACTION", "e1_tense": "PRESENT", "e1_aspect": "NONE", "e1_off": 2065, "e2_word": "says", "e2_class": "REPORTING", "e2_tense": "PRESENT", "e2_aspect": "NONE", "e2_off": 780, "same_sentence": false, "text_order": "e2_first", "e1_sentence": "", "e2_sentence": "", "signal": "", "relation": "SIMULTANEOUS"}, {"pair_id": "VOA19980303.1600.2745.tml_ei50015_ei50014", "e1_word": "recruiting", "e1_class": "OCCURRENCE", "e1_tense": "PRESPART", "e1_aspect": "NONE", "e1_off": 2332, "e2_word": "grew", "e2_class": "OCCURRENCE", "e2_tense": "PAST", "e2_aspect": "NONE", "e2_off": 2130, "same_sentence": false, "text_order": "e2_first", "e1_sentence": "", "e2_sentence": "", "signal": "", "relation": "BEFORE"}, {"pair_id": "VOA19980303.1600.2745.tml_ei50016_ei50005", "e1_word": "says", "e1_class": "REPORTING", "e1_tense": "PRESENT", "e1_aspect": "NONE", "e1_off": 2415, "e2_word": "says", "e2_class": "REPORTING", "e2_tense": "PRESENT", "e2_aspect": "NONE", "e2_off": 780, "same_sentence": false, "text_order": "e2_first", "e1_sentence": "", "e2_sentence": "", "signal": "", "relation": "IDENTITY"}, {"pair_id": "VOA19980303.1600.2745.tml_ei50017_ei50014", "e1_word": "growth", "e1_class": "OCCURRENCE", "e1_tense": "NONE", "e1_aspect": "NONE", "e1_off": 2467, "e2_word": "grew", "e2_class": "OCCURRENCE", "e2_tense": "PAST", "e2_aspect": "NONE", "e2_off": 2130, "same_sentence": false, "text_order": "e2_first", "e1_sentence": "", "e2_sentence": "", "signal": "", "relation": "IDENTITY"}, {"pair_id": "VOA19980303.1600.2745.tml_ei50022_ei50021", "e1_word": "rise", "e1_class": "OCCURRENCE", "e1_tense": "NONE", "e1_aspect": "NONE", "e1_off": 3192, "e2_word": "jumped", "e2_class": "OCCURRENCE", "e2_tense": "PAST", "e2_aspect": "NONE", "e2_off": 3102, "same_sentence": true, "text_order": "e2_first", "e1_sentence": "", "e2_sentence": "", "signal": "", "relation": "IDENTITY"}, {"pair_id": "VOA19980303.1600.2745.tml_ei50023_ei50016", "e1_word": "says", "e1_class": "REPORTING", "e1_tense": "PRESENT", "e1_aspect": "NONE", "e1_off": 3257, "e2_word": "says", "e2_class": "REPORTING", "e2_tense": "PRESENT", "e2_aspect": "NONE", "e2_off": 2415, "same_sentence": false, "text_order": "e2_first", "e1_sentence": "", "e2_sentence": "", "signal": "", "relation": "IDENTITY"}, {"pair_id": "VOA19980303.1600.2745.tml_ei50025_ei50026", "e1_word": "becoming", "e1_class": "I_STATE", "e1_tense": "PRESENT", "e1_aspect": "PROGRESSIVE", "e1_off": 3413, "e2_word": "successful", "e2_class": "I_STATE", "e2_tense": "NONE", "e2_aspect": "NONE", "e2_off": 3476, "same_sentence": true, "text_order": "e1_first", "e1_sentence": "", "e2_sentence": "", "signal": "", "relation": "ENDED_BY"}, {"pair_id": "VOA19980303.1600.2745.tml_ei50027_ei50028", "e1_word": "recruiting", "e1_class": "OCCURRENCE", "e1_tense": "PRESPART", "e1_aspect": "NONE", "e1_off": 3532, "e2_word": "use", "e2_class": "OCCURRENCE", "e2_tense": "NONE", "e2_aspect": "NONE", "e2_off": 3616, "same_sentence": true, "text_order": "e1_first", "e1_sentence": "", "e2_sentence": "", "signal": "", "relation": "INCLUDES"}, {"pair_id": "VOA19980303.1600.2745.tml_ei50027_ei50029", "e1_word": "recruiting", "e1_class": "OCCURRENCE", "e1_tense": "PRESPART", "e1_aspect": "NONE", "e1_off": 3532, "e2_word": "promotion", "e2_class": "OCCURRENCE", "e2_tense": "NONE", "e2_aspect": "NONE", "e2_off": 3694, "same_sentence": false, "text_order": "e1_first", "e1_sentence": "", "e2_sentence": "", "signal": "", "relation": "INCLUDES"}, {"pair_id": "VOA19980303.1600.2745.tml_ei50033_ei50030", "e1_word": "become", "e1_class": "I_STATE", "e1_tense": "PRESENT", "e1_aspect": "PERFECTIVE", "e1_off": 4164, "e2_word": "helped", "e2_class": "I_STATE", "e2_tense": "PRESENT", "e2_aspect": "PERFECTIVE", "e2_off": 3800, "same_sentence": false, "text_order": "e2_first", "e1_sentence": "", "e2_sentence": "", "signal": "", "relation": "SIMULTANEOUS"}, {"pair_id": "VOA19980303.1600.2745.tml_ei50037_ei50023", "e1_word": "says", "e1_class": "REPORTING", "e1_tense": "PRESENT", "e1_aspect": "NONE", "e1_off": 4745, "e2_word": "says", "e2_class": "REPORTING", "e2_tense": "PRESENT", "e2_aspect": "NONE", "e2_off": 3257, "same_sentence": false, "text_order": "e2_first", "e1_sentence": "", "e2_sentence": "", "signal": "", "relation": "IDENTITY"}, {"pair_id": "VOA19980303.1600.2745.tml_ei50039_ei50041", "e1_word": "approach", "e1_class": "I_STATE", "e1_tense": "NONE", "e1_aspect": "NONE", "e1_off": 4914, "e2_word": "believe", "e2_class": "I_STATE", "e2_tense": "PRESENT", "e2_aspect": "NONE", "e2_off": 5211, "same_sentence": false, "text_order": "e1_first", "e1_sentence": "", "e2_sentence": "", "signal": "", "relation": "BEFORE"}, {"pair_id": "VOA19980303.1600.2745.tml_ei50041_ei50042", "e1_word": "believe", "e1_class": "I_STATE", "e1_tense": "PRESENT", "e1_aspect": "NONE", "e1_off": 5211, "e2_word": "believe", "e2_class": "I_STATE", "e2_tense": "PRESENT", "e2_aspect": "NONE", "e2_off": 5286, "same_sentence": true, "text_order": "e1_first", "e1_sentence": "", "e2_sentence": "", "signal": "", "relation": "INCLUDES"}, {"pair_id": "VOA19980303.1600.2745.tml_ei50045_ei50044", "e1_word": "trying", "e1_class": "I_ACTION", "e1_tense": "PRESPART", "e1_aspect": "NONE", "e1_off": 5544, "e2_word": "Battle", "e2_class": "OCCURRENCE", "e2_tense": "NONE", "e2_aspect": "NONE", "e2_off": 5411, "same_sentence": false, "text_order": "e2_first", "e1_sentence": "", "e2_sentence": "", "signal": "", "relation": "IS_INCLUDED"}, {"pair_id": "VOA19980303.1600.2745.tml_ei50044_ei50046", "e1_word": "Battle", "e1_class": "OCCURRENCE", "e1_tense": "NONE", "e1_aspect": "NONE", "e1_off": 5411, "e2_word": "take", "e2_class": "OCCURRENCE", "e2_tense": "INFINITIVE", "e2_aspect": "NONE", "e2_off": 5596, "same_sentence": false, "text_order": "e1_first", "e1_sentence": "", "e2_sentence": "", "signal": "", "relation": "INCLUDES"}, {"pair_id": "VOA19980303.1600.2745.tml_ei50045_ei50046", "e1_word": "trying", "e1_class": "I_ACTION", "e1_tense": "PRESPART", "e1_aspect": "NONE", "e1_off": 5544, "e2_word": "take", "e2_class": "OCCURRENCE", "e2_tense": "INFINITIVE", "e2_aspect": "NONE", "e2_off": 5596, "same_sentence": true, "text_order": "e1_first", "e1_sentence": "", "e2_sentence": "", "signal": "", "relation": "SIMULTANEOUS"}, {"pair_id": "VOA19980303.1600.2745.tml_ei50047_ei50037", "e1_word": "notes", "e1_class": "REPORTING", "e1_tense": "PRESENT", "e1_aspect": "NONE", "e1_off": 5675, "e2_word": "says", "e2_class": "REPORTING", "e2_tense": "PRESENT", "e2_aspect": "NONE", "e2_off": 4745, "same_sentence": false, "text_order": "e2_first", "e1_sentence": "", "e2_sentence": "", "signal": "", "relation": "IS_INCLUDED"}, {"pair_id": "VOA19980303.1600.2745.tml_ei50049_ei50048", "e1_word": "ability", "e1_class": "I_STATE", "e1_tense": "NONE", "e1_aspect": "NONE", "e1_off": 5876, "e2_word": "opening", "e2_class": "OCCURRENCE", "e2_tense": "PRESENT", "e2_aspect": "NONE", "e2_off": 5786, "same_sentence": true, "text_order": "e2_first", "e1_sentence": "", "e2_sentence": "", "signal": "", "relation": "BEFORE"}, {"pair_id": "VOA19980303.1600.2745.tml_ei50051_ei50037", "e1_word": "says", "e1_class": "REPORTING", "e1_tense": "PRESENT", "e1_aspect": "NONE", "e1_off": 6050, "e2_word": "says", "e2_class": "REPORTING", "e2_tense": "PRESENT", "e2_aspect": "NONE", "e2_off": 4745, "same_sentence": false, "text_order": "e2_first", "e1_sentence": "", "e2_sentence": "", "signal": "", "relation": "SIMULTANEOUS"}, {"pair_id": "VOA19980303.1600.2745.tml_ei50055_ei50051", "e1_word": "say", "e1_class": "REPORTING", "e1_tense": "PRESENT", "e1_aspect": "NONE", "e1_off": 6460, "e2_word": "says", "e2_class": "REPORTING", "e2_tense": "PRESENT", "e2_aspect": "NONE", "e2_off": 6050, "same_sentence": false, "text_order": "e2_first", "e1_sentence": "", "e2_sentence": "", "signal": "", "relation": "SIMULTANEOUS"}, {"pair_id": "VOA19980303.1600.2745.tml_ei50057_ei50056", "e1_word": "beginning", "e1_class": "ASPECTUAL", "e1_tense": "PRESENT", "e1_aspect": "PROGRESSIVE", "e1_off": 6748, "e2_word": "increase", "e2_class": "OCCURRENCE", "e2_tense": "INFINITIVE", "e2_aspect": "NONE", "e2_off": 6534, "same_sentence": false, "text_order": "e2_first", "e1_sentence": "", "e2_sentence": "", "signal": "", "relation": "BEFORE"}, {"pair_id": "VOA19980303.1600.2745.tml_ei50060_ei50058", "e1_word": "have", "e1_class": "REPORTING", "e1_tense": "PRESENT", "e1_aspect": "PERFECTIVE", "e1_off": 6939, "e2_word": "report", "e2_class": "REPORTING", "e2_tense": "NONE", "e2_aspect": "NONE", "e2_off": 6820, "same_sentence": true, "text_order": "e2_first", "e1_sentence": "", "e2_sentence": "", "signal": "", "relation": "BEFORE"}]